MANIFEST.in
README.md
setup.py
django_eventy.egg-info/PKG-INFO
django_eventy.egg-info/SOURCES.txt
django_eventy.egg-info/dependency_links.txt
django_eventy.egg-info/requires.txt
django_eventy.egg-info/top_level.txt
django_eventy.egg-info/zip-safe
eventy/__init__.py
eventy/admin.py
eventy/managers.py
eventy/models.py
eventy/urls.py
eventy/utils.py
eventy/views.py
eventy/templatetags/.eventy_tags.py.swo
eventy/templatetags/.eventy_tags.py.swp
eventy/templatetags/__init__.py
eventy/templatetags/__init__.pyc
eventy/templatetags/eventy_tags.py
eventy/templatetags/eventy_tags.pyc