Metadata-Version: 1.0
Name: django-eventy
Version: 0.1.1
Summary: A really simple event manager with no recurring abilities for django.
Home-page: http://github.com/powellc/django-eventy
Author: Colin Powell
Author-email: colin@onecardinal.com
License: BSD
Download-URL: http://github.com/powellc/django-eventy/downloads
Platform: UNKNOWN
Classifier: Development Status :: 4 - Beta
Classifier: Environment :: Web Environment
Classifier: Intended Audience :: Developers
Classifier: License :: OSI Approved :: BSD License
Classifier: Operating System :: OS Independent
Classifier: Programming Language :: Python
Classifier: Framework :: Django
